README.md
setup.py
wikieds.py
wikieds.egg-info/PKG-INFO
wikieds.egg-info/SOURCES.txt
wikieds.egg-info/dependency_links.txt
wikieds.egg-info/entry_points.txt
wikieds.egg-info/top_level.txt