Metadata-Version: 1.2
Name: wikieds
Version: 0.0.2
Summary: Command line tool to Print a markdown summary of editors for a Wikipedia article.
Home-page: http://github.com/edsu/wikieds
Author: Ed Summers
Author-email: ehs@pobox.com
License: UNKNOWN
Platform: UNKNOWN
Requires-Python: >=3.6
